{
  "version": 2,
  "extractor": "papercropper",
  "figures": [
    {
      "url": "assets/figures/arxiv/2605.26471v1/fig-001.webp",
      "caption": "",
      "page": 0,
      "index": 1,
      "width": 1797,
      "height": 920,
      "label": "Figure"
    },
    {
      "url": "assets/figures/arxiv/2605.26471v1/fig-002.webp",
      "caption": "",
      "page": 0,
      "index": 2,
      "width": 911,
      "height": 601,
      "label": "Figure"
    },
    {
      "url": "assets/figures/arxiv/2605.26471v1/fig-003.webp",
      "caption": "",
      "page": 0,
      "index": 3,
      "width": 1831,
      "height": 855,
      "label": "Figure"
    },
    {
      "url": "assets/figures/arxiv/2605.26471v1/fig-004.webp",
      "caption": "",
      "page": 0,
      "index": 4,
      "width": 1837,
      "height": 918,
      "label": "Figure"
    },
    {
      "url": "assets/figures/arxiv/2605.26471v1/fig-005.webp",
      "caption": "",
      "page": 0,
      "index": 5,
      "width": 1854,
      "height": 537,
      "label": "Figure"
    },
    {
      "url": "assets/figures/arxiv/2605.26471v1/fig-006.webp",
      "caption": "",
      "page": 0,
      "index": 6,
      "width": 839,
      "height": 861,
      "label": "Figure"
    },
    {
      "url": "assets/figures/arxiv/2605.26471v1/fig-007.webp",
      "caption": "",
      "page": 0,
      "index": 7,
      "width": 909,
      "height": 700,
      "label": "Figure"
    },
    {
      "url": "assets/figures/arxiv/2605.26471v1/fig-008.webp",
      "caption": "",
      "page": 0,
      "index": 8,
      "width": 905,
      "height": 526,
      "label": "Figure"
    },
    {
      "url": "assets/figures/arxiv/2605.26471v1/fig-009.webp",
      "caption": "",
      "page": 0,
      "index": 9,
      "width": 1844,
      "height": 509,
      "label": "Figure"
    }
  ]
}